README.md
setup.py
syncitems/__init__.py
syncitems/models.py
syncitems/syncitems.py
syncitems.egg-info/PKG-INFO
syncitems.egg-info/SOURCES.txt
syncitems.egg-info/dependency_links.txt
syncitems.egg-info/requires.txt
syncitems.egg-info/top_level.txt
syncitems/services/__init__.py
syncitems/services/execute_log.py
syncitems/services/sync_data.py