Metadata-Version: 1.0
Name: syncitems
Version: 0.1.0
Summary: Sync item between clients with server
Home-page: https://github.com/ipconfiger/syncitems
Author: Alexander.Li
Author-email: superpowerlee@gmail.com
License: GPL-3.0
Platform: a
Platform: n
Platform: y
